anstrip/__init__.py
anstrip/__init__.pyi
anstrip/py.typed
anstrip-0.2.2.dist-info/LICENSE
anstrip-0.2.2.dist-info/METADATA
anstrip-0.2.2.dist-info/WHEEL
anstrip-0.2.2.dist-info/top_level.txt
anstrip-0.2.2.dist-info/RECORD
