Metadata-Version: 2.1
Name: anstrip
Version: 0.2.2
Summary: anstrip is a minimal library to strip ANSI sequences from strings.
Author-email: Qexat <contact@qexat.com>
License: MIT License
Project-URL: source, https://github.com/qexat/anstrip
Keywords: ansi,escape sequence,SGR,ECMA,strip
Requires-Python: >=3.10
License-File: LICENSE
Provides-Extra: dev
Requires-Dist: pytest >=7.4 ; extra == 'dev'
Requires-Dist: coverage >=7.4 ; extra == 'dev'
Requires-Dist: pyright >=1.1 ; extra == 'dev'
Requires-Dist: build ; extra == 'dev'
Requires-Dist: twine ; extra == 'dev'
